thefirstock/__init__.py
thefirstock/thefirstock.py
thefirstock/Variables/__init__.py
thefirstock/Variables/enums.py
thefirstock/Variables/fixedParams.py
thefirstock/firstockModules/__init__.py
thefirstock/firstockModules/firstockWebSockets.py
thefirstock/loginNProfile/__init__.py
thefirstock/loginNProfile/loginFirstock.py
thefirstock/loginNProfile/logoutFirstock.py
thefirstock/loginNProfile/userDetailsFirstock.py
thefirstock/loginNProfile/loginFunctionality/__init__.py
thefirstock/loginNProfile/loginFunctionality/base.py
thefirstock/loginNProfile/loginFunctionality/execution.py
thefirstock/loginNProfile/loginFunctionality/functions.py
thefirstock/loginNProfile/logoutFunctionality/__init__.py
thefirstock/loginNProfile/logoutFunctionality/base.py
thefirstock/loginNProfile/logoutFunctionality/execution.py
thefirstock/loginNProfile/logoutFunctionality/functions.py
thefirstock/loginNProfile/userDetailsFunctionality/__init__.py
thefirstock/loginNProfile/userDetailsFunctionality/base.py
thefirstock/loginNProfile/userDetailsFunctionality/execution.py
thefirstock/loginNProfile/userDetailsFunctionality/functions.py
thefirstock/marketConnect/__init__.py
thefirstock/marketConnect/getIndexListFirstock.py
thefirstock/marketConnect/getMultiQuoteFirstock.py
thefirstock/marketConnect/getMultiQuoteLTPFirstock.py
thefirstock/marketConnect/getOptionChainFirstock.py
thefirstock/marketConnect/getQuoteLTPFirstock.py
thefirstock/marketConnect/getQuotesFirstock.py
thefirstock/marketConnect/getSecurityInfoFirstock.py
thefirstock/marketConnect/optionGreekFirstock.py
thefirstock/marketConnect/searchScripsFirstock.py
thefirstock/marketConnect/spanCalculatorFirstock.py
thefirstock/marketConnect/timePriceSeriesFirstock.py
thefirstock/marketConnect/getIndexListFunctionality/__init__.py
thefirstock/marketConnect/getIndexListFunctionality/base.py
thefirstock/marketConnect/getIndexListFunctionality/execution.py
thefirstock/marketConnect/getIndexListFunctionality/functions.py
test_firstock-0.0.3.dist-info/LICENSE
test_firstock-0.0.3.dist-info/METADATA
test_firstock-0.0.3.dist-info/WHEEL
test_firstock-0.0.3.dist-info/top_level.txt
test_firstock-0.0.3.dist-info/RECORD
