Metadata-Version: 2.1
Name: test-firstock
Version: 0.0.3
Author: SanjayUK
Author-email: sanjay.firstock@gmail.com
Classifier: Programming Language :: Python :: 3
Classifier: Operating System :: OS Independent
Classifier: Intended Audience :: Developers
Classifier: License :: OSI Approved :: MIT License
Classifier: Programming Language :: Python :: 3.10
Classifier: Topic :: Software Development :: Libraries :: Python Modules
Requires-Python: >=3.7
License-File: LICENSE
Requires-Dist: requests
Requires-Dist: ws4py
Requires-Dist: pydantic
Requires-Dist: pydantic[email]
Requires-Dist: python-dateutil
